{
  "projectName" : "hadoop",
  "repoUrl" : null,
  "merges" : [ {
    "mergeCommit" : "9da62f33beb1373e468055e8df92f493bee97a82",
    "parent1" : "456bb8a3e01bb41b02cc64a5cff149446668afab",
    "parent2" : "03aa70fe19e06a0b3d637acc7b5db4c955f0a693",
    "numConflictFiles" : 1,
    "numJavaConflictFiles" : 1,
    "numConflictChunks" : 1,
    "isMultiModule" : true,
    "coverage" : null,
    "totalExecutionTime" : 998,
    "compilationResult" : {
      "moduleResults" : [ {
        "moduleName" : "Apache Hadoop Main",
        "status" : "SUCCESS",
        "timeElapsed" : 0.484
      }, {
        "moduleName" : "Apache Hadoop Build Tools",
        "status" : "SUCCESS",
        "timeElapsed" : 3.021
      }, {
        "moduleName" : "Apache Hadoop Project POM",
        "status" : "SUCCESS",
        "timeElapsed" : 0.553
      }, {
        "moduleName" : "Apache Hadoop Annotations",
        "status" : "SUCCESS",
        "timeElapsed" : 1.152
      }, {
        "moduleName" : "Apache Hadoop Project Dist POM",
        "status" : "SUCCESS",
        "timeElapsed" : 0.095
      }, {
        "moduleName" : "Apache Hadoop Assemblies",
        "status" : "SUCCESS",
        "timeElapsed" : 0.143
      }, {
        "moduleName" : "Apache Hadoop Maven Plugins",
        "status" : "SUCCESS",
        "timeElapsed" : 4.021
      }, {
        "moduleName" : "Apache Hadoop MiniKDC",
        "status" : "SUCCESS",
        "timeElapsed" : 10.536
      }, {
        "moduleName" : "Apache Hadoop Auth",
        "status" : "FAILURE",
        "timeElapsed" : 428.0
      }, {
        "moduleName" : "Apache Hadoop Auth Examples",
        "status" : "SKIPPED",
        "timeElapsed" : 0.0
      }, {
        "moduleName" : "Apache Hadoop Common",
        "status" : "SKIPPED",
        "timeElapsed" : 0.0
      }, {
        "moduleName" : "Apache Hadoop NFS",
        "status" : "SKIPPED",
        "timeElapsed" : 0.0
      }, {
        "moduleName" : "Apache Hadoop KMS",
        "status" : "SKIPPED",
        "timeElapsed" : 0.0
      }, {
        "moduleName" : "Apache Hadoop Registry",
        "status" : "SKIPPED",
        "timeElapsed" : 0.0
      }, {
        "moduleName" : "Apache Hadoop Common Project",
        "status" : "SUCCESS",
        "timeElapsed" : 0.033
      }, {
        "moduleName" : "Apache Hadoop HDFS Client",
        "status" : "SKIPPED",
        "timeElapsed" : 0.0
      }, {
        "moduleName" : "Apache Hadoop HDFS",
        "status" : "SKIPPED",
        "timeElapsed" : 0.0
      }, {
        "moduleName" : "Apache Hadoop HDFS Native Client",
        "status" : "SKIPPED",
        "timeElapsed" : 0.0
      }, {
        "moduleName" : "Apache Hadoop HttpFS",
        "status" : "SKIPPED",
        "timeElapsed" : 0.0
      }, {
        "moduleName" : "Apache Hadoop HDFS-NFS",
        "status" : "SKIPPED",
        "timeElapsed" : 0.0
      }, {
        "moduleName" : "Apache Hadoop HDFS-RBF",
        "status" : "SKIPPED",
        "timeElapsed" : 0.0
      }, {
        "moduleName" : "Apache Hadoop HDFS Project",
        "status" : "SUCCESS",
        "timeElapsed" : 0.028
      }, {
        "moduleName" : "Apache Hadoop YARN",
        "status" : "SUCCESS",
        "timeElapsed" : 0.026
      }, {
        "moduleName" : "Apache Hadoop YARN API",
        "status" : "SKIPPED",
        "timeElapsed" : 0.0
      }, {
        "moduleName" : "Apache Hadoop YARN Common",
        "status" : "SKIPPED",
        "timeElapsed" : 0.0
      }, {
        "moduleName" : "Apache Hadoop YARN Server",
        "status" : "SUCCESS",
        "timeElapsed" : 0.029
      }, {
        "moduleName" : "Apache Hadoop YARN Server Common",
        "status" : "SKIPPED",
        "timeElapsed" : 0.0
      }, {
        "moduleName" : "Apache Hadoop YARN NodeManager",
        "status" : "SKIPPED",
        "timeElapsed" : 0.0
      }, {
        "moduleName" : "Apache Hadoop YARN Web Proxy",
        "status" : "SKIPPED",
        "timeElapsed" : 0.0
      }, {
        "moduleName" : "Apache Hadoop YARN ApplicationHistoryService",
        "status" : "SKIPPED",
        "timeElapsed" : 0.0
      }, {
        "moduleName" : "Apache Hadoop YARN Timeline Service",
        "status" : "SKIPPED",
        "timeElapsed" : 0.0
      }, {
        "moduleName" : "Apache Hadoop YARN ResourceManager",
        "status" : "SKIPPED",
        "timeElapsed" : 0.0
      }, {
        "moduleName" : "Apache Hadoop YARN Server Tests",
        "status" : "SKIPPED",
        "timeElapsed" : 0.0
      }, {
        "moduleName" : "Apache Hadoop YARN Client",
        "status" : "SKIPPED",
        "timeElapsed" : 0.0
      }, {
        "moduleName" : "Apache Hadoop YARN SharedCacheManager",
        "status" : "SKIPPED",
        "timeElapsed" : 0.0
      }, {
        "moduleName" : "Apache Hadoop YARN Timeline Plugin Storage",
        "status" : "SKIPPED",
        "timeElapsed" : 0.0
      }, {
        "moduleName" : "Apache Hadoop YARN TimelineService HBase Backend",
        "status" : "SUCCESS",
        "timeElapsed" : 0.032
      }, {
        "moduleName" : "Apache Hadoop YARN TimelineService HBase Common",
        "status" : "SKIPPED",
        "timeElapsed" : 0.0
      }, {
        "moduleName" : "Apache Hadoop YARN TimelineService HBase Client",
        "status" : "SKIPPED",
        "timeElapsed" : 0.0
      }, {
        "moduleName" : "Apache Hadoop YARN TimelineService HBase Servers",
        "status" : "SUCCESS",
        "timeElapsed" : 0.069
      }, {
        "moduleName" : "Apache Hadoop YARN TimelineService HBase Server 1.2",
        "status" : "SKIPPED",
        "timeElapsed" : 0.0
      }, {
        "moduleName" : "Apache Hadoop YARN TimelineService HBase tests",
        "status" : "SKIPPED",
        "timeElapsed" : 0.0
      }, {
        "moduleName" : "Apache Hadoop YARN Router",
        "status" : "SKIPPED",
        "timeElapsed" : 0.0
      }, {
        "moduleName" : "Apache Hadoop YARN TimelineService DocumentStore",
        "status" : "SKIPPED",
        "timeElapsed" : 0.0
      }, {
        "moduleName" : "Apache Hadoop YARN Applications",
        "status" : "SUCCESS",
        "timeElapsed" : 0.029
      }, {
        "moduleName" : "Apache Hadoop YARN DistributedShell",
        "status" : "SKIPPED",
        "timeElapsed" : 0.0
      }, {
        "moduleName" : "Apache Hadoop YARN Unmanaged Am Launcher",
        "status" : "SKIPPED",
        "timeElapsed" : 0.0
      }, {
        "moduleName" : "Apache Hadoop MapReduce Client",
        "status" : "SKIPPED",
        "timeElapsed" : 0.0
      }, {
        "moduleName" : "Apache Hadoop MapReduce Core",
        "status" : "SKIPPED",
        "timeElapsed" : 0.0
      }, {
        "moduleName" : "Apache Hadoop MapReduce Common",
        "status" : "SKIPPED",
        "timeElapsed" : 0.0
      }, {
        "moduleName" : "Apache Hadoop MapReduce Shuffle",
        "status" : "SKIPPED",
        "timeElapsed" : 0.0
      }, {
        "moduleName" : "Apache Hadoop MapReduce App",
        "status" : "SKIPPED",
        "timeElapsed" : 0.0
      }, {
        "moduleName" : "Apache Hadoop MapReduce HistoryServer",
        "status" : "SKIPPED",
        "timeElapsed" : 0.0
      }, {
        "moduleName" : "Apache Hadoop MapReduce JobClient",
        "status" : "SKIPPED",
        "timeElapsed" : 0.0
      }, {
        "moduleName" : "Apache Hadoop Mini-Cluster",
        "status" : "SKIPPED",
        "timeElapsed" : 0.0
      }, {
        "moduleName" : "Apache Hadoop YARN Services",
        "status" : "SUCCESS",
        "timeElapsed" : 0.027
      }, {
        "moduleName" : "Apache Hadoop YARN Services Core",
        "status" : "SKIPPED",
        "timeElapsed" : 0.0
      }, {
        "moduleName" : "Apache Hadoop YARN Services API",
        "status" : "SKIPPED",
        "timeElapsed" : 0.0
      }, {
        "moduleName" : "Apache Hadoop YARN Application Catalog",
        "status" : "SUCCESS",
        "timeElapsed" : 0.027
      }, {
        "moduleName" : "Apache Hadoop YARN Application Catalog Webapp",
        "status" : "SKIPPED",
        "timeElapsed" : 0.0
      }, {
        "moduleName" : "Apache Hadoop YARN Application Catalog Docker Image",
        "status" : "SKIPPED",
        "timeElapsed" : 0.0
      }, {
        "moduleName" : "Apache Hadoop YARN Application MaWo",
        "status" : "SUCCESS",
        "timeElapsed" : 0.028
      }, {
        "moduleName" : "Apache Hadoop YARN Application MaWo Core",
        "status" : "SKIPPED",
        "timeElapsed" : 0.0
      }, {
        "moduleName" : "Apache Hadoop YARN Site",
        "status" : "SUCCESS",
        "timeElapsed" : 0.026
      }, {
        "moduleName" : "Apache Hadoop YARN Registry",
        "status" : "SKIPPED",
        "timeElapsed" : 0.0
      }, {
        "moduleName" : "Apache Hadoop YARN UI",
        "status" : "SUCCESS",
        "timeElapsed" : 0.026
      }, {
        "moduleName" : "Apache Hadoop YARN CSI",
        "status" : "SKIPPED",
        "timeElapsed" : 0.0
      }, {
        "moduleName" : "Apache Hadoop YARN Project",
        "status" : "SKIPPED",
        "timeElapsed" : 0.0
      }, {
        "moduleName" : "Apache Hadoop MapReduce HistoryServer Plugins",
        "status" : "SKIPPED",
        "timeElapsed" : 0.0
      }, {
        "moduleName" : "Apache Hadoop MapReduce NativeTask",
        "status" : "SKIPPED",
        "timeElapsed" : 0.0
      }, {
        "moduleName" : "Apache Hadoop MapReduce Uploader",
        "status" : "SKIPPED",
        "timeElapsed" : 0.0
      }, {
        "moduleName" : "Apache Hadoop MapReduce Examples",
        "status" : "SKIPPED",
        "timeElapsed" : 0.0
      }, {
        "moduleName" : "Apache Hadoop MapReduce",
        "status" : "SKIPPED",
        "timeElapsed" : 0.0
      }, {
        "moduleName" : "Apache Hadoop MapReduce Streaming",
        "status" : "SKIPPED",
        "timeElapsed" : 0.0
      }, {
        "moduleName" : "Apache Hadoop Distributed Copy",
        "status" : "SKIPPED",
        "timeElapsed" : 0.0
      }, {
        "moduleName" : "Apache Hadoop Archives",
        "status" : "SKIPPED",
        "timeElapsed" : 0.0
      }, {
        "moduleName" : "Apache Hadoop Archive Logs",
        "status" : "SKIPPED",
        "timeElapsed" : 0.0
      }, {
        "moduleName" : "Apache Hadoop Rumen",
        "status" : "SKIPPED",
        "timeElapsed" : 0.0
      }, {
        "moduleName" : "Apache Hadoop Gridmix",
        "status" : "SKIPPED",
        "timeElapsed" : 0.0
      }, {
        "moduleName" : "Apache Hadoop Data Join",
        "status" : "SKIPPED",
        "timeElapsed" : 0.0
      }, {
        "moduleName" : "Apache Hadoop Extras",
        "status" : "SKIPPED",
        "timeElapsed" : 0.0
      }, {
        "moduleName" : "Apache Hadoop Pipes",
        "status" : "SUCCESS",
        "timeElapsed" : 0.026
      }, {
        "moduleName" : "Apache Hadoop OpenStack support",
        "status" : "SKIPPED",
        "timeElapsed" : 0.0
      }, {
        "moduleName" : "Apache Hadoop Amazon Web Services support",
        "status" : "SKIPPED",
        "timeElapsed" : 0.0
      }, {
        "moduleName" : "Apache Hadoop Kafka Library support",
        "status" : "SKIPPED",
        "timeElapsed" : 0.0
      }, {
        "moduleName" : "Apache Hadoop Azure support",
        "status" : "SKIPPED",
        "timeElapsed" : 0.0
      }, {
        "moduleName" : "Apache Hadoop Aliyun OSS support",
        "status" : "SKIPPED",
        "timeElapsed" : 0.0
      }, {
        "moduleName" : "Apache Hadoop Client Aggregator",
        "status" : "SKIPPED",
        "timeElapsed" : 0.0
      }, {
        "moduleName" : "Apache Hadoop Scheduler Load Simulator",
        "status" : "SKIPPED",
        "timeElapsed" : 0.0
      }, {
        "moduleName" : "Apache Hadoop Resource Estimator Service",
        "status" : "SKIPPED",
        "timeElapsed" : 0.0
      }, {
        "moduleName" : "Apache Hadoop Azure Data Lake support",
        "status" : "SKIPPED",
        "timeElapsed" : 0.0
      }, {
        "moduleName" : "Apache Hadoop Image Generation Tool",
        "status" : "SKIPPED",
        "timeElapsed" : 0.0
      }, {
        "moduleName" : "Apache Hadoop Tools Dist",
        "status" : "SKIPPED",
        "timeElapsed" : 0.0
      }, {
        "moduleName" : "Apache Hadoop Tools",
        "status" : "SUCCESS",
        "timeElapsed" : 0.028
      }, {
        "moduleName" : "Apache Hadoop Client API",
        "status" : "SKIPPED",
        "timeElapsed" : 0.0
      }, {
        "moduleName" : "Apache Hadoop Client Runtime",
        "status" : "SKIPPED",
        "timeElapsed" : 0.0
      }, {
        "moduleName" : "Apache Hadoop Client Packaging Invariants",
        "status" : "SKIPPED",
        "timeElapsed" : 0.0
      }, {
        "moduleName" : "Apache Hadoop Client Test Minicluster",
        "status" : "SKIPPED",
        "timeElapsed" : 0.0
      }, {
        "moduleName" : "Apache Hadoop Client Packaging Invariants for Test",
        "status" : "SKIPPED",
        "timeElapsed" : 0.0
      }, {
        "moduleName" : "Apache Hadoop Client Packaging Integration Tests",
        "status" : "SKIPPED",
        "timeElapsed" : 0.0
      }, {
        "moduleName" : "Apache Hadoop Distribution",
        "status" : "SKIPPED",
        "timeElapsed" : 0.0
      }, {
        "moduleName" : "Apache Hadoop Client Modules",
        "status" : "SUCCESS",
        "timeElapsed" : 0.025
      }, {
        "moduleName" : "Apache Hadoop Cloud Storage",
        "status" : "SKIPPED",
        "timeElapsed" : 0.0
      }, {
        "moduleName" : "Apache Hadoop Cloud Storage Project",
        "status" : "SUCCESS",
        "timeElapsed" : 0.029
      } ],
      "buildStatus" : "FAILURE",
      "totalTime" : 451.0
    },
    "testResults" : {
      "runNum" : 102,
      "failuresNum" : 0,
      "errorsNum" : 0,
      "skippedNum" : 0,
      "elapsedTime" : 92.117004,
      "projectDir" : "C:\\Users\\vova\\Documents\\BernUni\\Semester3\\Thesis\\ci-cd-merge-resolver\\ci-cd-merge-resolver\\temp\\projects\\hadoop"
    },
    "variantsExecution" : {
      "executionTimeSeconds" : 470,
      "variants" : [ {
        "variantName" : "hadoop_0",
        "compilationResult" : {
          "moduleResults" : [ {
            "moduleName" : "Apache Hadoop Main",
            "status" : "SUCCESS",
            "timeElapsed" : 0.391
          }, {
            "moduleName" : "Apache Hadoop Build Tools",
            "status" : "SUCCESS",
            "timeElapsed" : 2.173
          }, {
            "moduleName" : "Apache Hadoop Project POM",
            "status" : "SUCCESS",
            "timeElapsed" : 0.375
          }, {
            "moduleName" : "Apache Hadoop Annotations",
            "status" : "SUCCESS",
            "timeElapsed" : 0.728
          }, {
            "moduleName" : "Apache Hadoop Project Dist POM",
            "status" : "SUCCESS",
            "timeElapsed" : 0.044
          }, {
            "moduleName" : "Apache Hadoop Assemblies",
            "status" : "SUCCESS",
            "timeElapsed" : 0.08
          }, {
            "moduleName" : "Apache Hadoop Maven Plugins",
            "status" : "SUCCESS",
            "timeElapsed" : 2.419
          }, {
            "moduleName" : "Apache Hadoop MiniKDC",
            "status" : "SUCCESS",
            "timeElapsed" : 9.041
          }, {
            "moduleName" : "Apache Hadoop Auth",
            "status" : "FAILURE",
            "timeElapsed" : 441.0
          }, {
            "moduleName" : "Apache Hadoop Auth Examples",
            "status" : "SKIPPED",
            "timeElapsed" : 0.0
          }, {
            "moduleName" : "Apache Hadoop Common",
            "status" : "SKIPPED",
            "timeElapsed" : 0.0
          }, {
            "moduleName" : "Apache Hadoop NFS",
            "status" : "SKIPPED",
            "timeElapsed" : 0.0
          }, {
            "moduleName" : "Apache Hadoop KMS",
            "status" : "SKIPPED",
            "timeElapsed" : 0.0
          }, {
            "moduleName" : "Apache Hadoop Registry",
            "status" : "SKIPPED",
            "timeElapsed" : 0.0
          }, {
            "moduleName" : "Apache Hadoop Common Project",
            "status" : "SUCCESS",
            "timeElapsed" : 0.065
          }, {
            "moduleName" : "Apache Hadoop HDFS Client",
            "status" : "SKIPPED",
            "timeElapsed" : 0.0
          }, {
            "moduleName" : "Apache Hadoop HDFS",
            "status" : "SKIPPED",
            "timeElapsed" : 0.0
          }, {
            "moduleName" : "Apache Hadoop HDFS Native Client",
            "status" : "SKIPPED",
            "timeElapsed" : 0.0
          }, {
            "moduleName" : "Apache Hadoop HttpFS",
            "status" : "SKIPPED",
            "timeElapsed" : 0.0
          }, {
            "moduleName" : "Apache Hadoop HDFS-NFS",
            "status" : "SKIPPED",
            "timeElapsed" : 0.0
          }, {
            "moduleName" : "Apache Hadoop HDFS-RBF",
            "status" : "SKIPPED",
            "timeElapsed" : 0.0
          }, {
            "moduleName" : "Apache Hadoop HDFS Project",
            "status" : "SUCCESS",
            "timeElapsed" : 0.063
          }, {
            "moduleName" : "Apache Hadoop YARN",
            "status" : "SUCCESS",
            "timeElapsed" : 0.047
          }, {
            "moduleName" : "Apache Hadoop YARN API",
            "status" : "SKIPPED",
            "timeElapsed" : 0.0
          }, {
            "moduleName" : "Apache Hadoop YARN Common",
            "status" : "SKIPPED",
            "timeElapsed" : 0.0
          }, {
            "moduleName" : "Apache Hadoop YARN Server",
            "status" : "SUCCESS",
            "timeElapsed" : 0.063
          }, {
            "moduleName" : "Apache Hadoop YARN Server Common",
            "status" : "SKIPPED",
            "timeElapsed" : 0.0
          }, {
            "moduleName" : "Apache Hadoop YARN NodeManager",
            "status" : "SKIPPED",
            "timeElapsed" : 0.0
          }, {
            "moduleName" : "Apache Hadoop YARN Web Proxy",
            "status" : "SKIPPED",
            "timeElapsed" : 0.0
          }, {
            "moduleName" : "Apache Hadoop YARN ApplicationHistoryService",
            "status" : "SKIPPED",
            "timeElapsed" : 0.0
          }, {
            "moduleName" : "Apache Hadoop YARN Timeline Service",
            "status" : "SKIPPED",
            "timeElapsed" : 0.0
          }, {
            "moduleName" : "Apache Hadoop YARN ResourceManager",
            "status" : "SKIPPED",
            "timeElapsed" : 0.0
          }, {
            "moduleName" : "Apache Hadoop YARN Server Tests",
            "status" : "SKIPPED",
            "timeElapsed" : 0.0
          }, {
            "moduleName" : "Apache Hadoop YARN Client",
            "status" : "SKIPPED",
            "timeElapsed" : 0.0
          }, {
            "moduleName" : "Apache Hadoop YARN SharedCacheManager",
            "status" : "SKIPPED",
            "timeElapsed" : 0.0
          }, {
            "moduleName" : "Apache Hadoop YARN Timeline Plugin Storage",
            "status" : "SKIPPED",
            "timeElapsed" : 0.0
          }, {
            "moduleName" : "Apache Hadoop YARN TimelineService HBase Backend",
            "status" : "SUCCESS",
            "timeElapsed" : 0.064
          }, {
            "moduleName" : "Apache Hadoop YARN TimelineService HBase Common",
            "status" : "SKIPPED",
            "timeElapsed" : 0.0
          }, {
            "moduleName" : "Apache Hadoop YARN TimelineService HBase Client",
            "status" : "SKIPPED",
            "timeElapsed" : 0.0
          }, {
            "moduleName" : "Apache Hadoop YARN TimelineService HBase Servers",
            "status" : "SUCCESS",
            "timeElapsed" : 0.056
          }, {
            "moduleName" : "Apache Hadoop YARN TimelineService HBase Server 1.2",
            "status" : "SKIPPED",
            "timeElapsed" : 0.0
          }, {
            "moduleName" : "Apache Hadoop YARN TimelineService HBase tests",
            "status" : "SKIPPED",
            "timeElapsed" : 0.0
          }, {
            "moduleName" : "Apache Hadoop YARN Router",
            "status" : "SKIPPED",
            "timeElapsed" : 0.0
          }, {
            "moduleName" : "Apache Hadoop YARN TimelineService DocumentStore",
            "status" : "SKIPPED",
            "timeElapsed" : 0.0
          }, {
            "moduleName" : "Apache Hadoop YARN Applications",
            "status" : "SUCCESS",
            "timeElapsed" : 0.054
          }, {
            "moduleName" : "Apache Hadoop YARN DistributedShell",
            "status" : "SKIPPED",
            "timeElapsed" : 0.0
          }, {
            "moduleName" : "Apache Hadoop YARN Unmanaged Am Launcher",
            "status" : "SKIPPED",
            "timeElapsed" : 0.0
          }, {
            "moduleName" : "Apache Hadoop MapReduce Client",
            "status" : "SKIPPED",
            "timeElapsed" : 0.0
          }, {
            "moduleName" : "Apache Hadoop MapReduce Core",
            "status" : "SKIPPED",
            "timeElapsed" : 0.0
          }, {
            "moduleName" : "Apache Hadoop MapReduce Common",
            "status" : "SKIPPED",
            "timeElapsed" : 0.0
          }, {
            "moduleName" : "Apache Hadoop MapReduce Shuffle",
            "status" : "SKIPPED",
            "timeElapsed" : 0.0
          }, {
            "moduleName" : "Apache Hadoop MapReduce App",
            "status" : "SKIPPED",
            "timeElapsed" : 0.0
          }, {
            "moduleName" : "Apache Hadoop MapReduce HistoryServer",
            "status" : "SKIPPED",
            "timeElapsed" : 0.0
          }, {
            "moduleName" : "Apache Hadoop MapReduce JobClient",
            "status" : "SKIPPED",
            "timeElapsed" : 0.0
          }, {
            "moduleName" : "Apache Hadoop Mini-Cluster",
            "status" : "SKIPPED",
            "timeElapsed" : 0.0
          }, {
            "moduleName" : "Apache Hadoop YARN Services",
            "status" : "SUCCESS",
            "timeElapsed" : 0.064
          }, {
            "moduleName" : "Apache Hadoop YARN Services Core",
            "status" : "SKIPPED",
            "timeElapsed" : 0.0
          }, {
            "moduleName" : "Apache Hadoop YARN Services API",
            "status" : "SKIPPED",
            "timeElapsed" : 0.0
          }, {
            "moduleName" : "Apache Hadoop YARN Application Catalog",
            "status" : "SUCCESS",
            "timeElapsed" : 0.047
          }, {
            "moduleName" : "Apache Hadoop YARN Application Catalog Webapp",
            "status" : "SKIPPED",
            "timeElapsed" : 0.0
          }, {
            "moduleName" : "Apache Hadoop YARN Application Catalog Docker Image",
            "status" : "SKIPPED",
            "timeElapsed" : 0.0
          }, {
            "moduleName" : "Apache Hadoop YARN Application MaWo",
            "status" : "SUCCESS",
            "timeElapsed" : 0.058
          }, {
            "moduleName" : "Apache Hadoop YARN Application MaWo Core",
            "status" : "SKIPPED",
            "timeElapsed" : 0.0
          }, {
            "moduleName" : "Apache Hadoop YARN Site",
            "status" : "SUCCESS",
            "timeElapsed" : 0.062
          }, {
            "moduleName" : "Apache Hadoop YARN Registry",
            "status" : "SKIPPED",
            "timeElapsed" : 0.0
          }, {
            "moduleName" : "Apache Hadoop YARN UI",
            "status" : "SUCCESS",
            "timeElapsed" : 0.063
          }, {
            "moduleName" : "Apache Hadoop YARN CSI",
            "status" : "SKIPPED",
            "timeElapsed" : 0.0
          }, {
            "moduleName" : "Apache Hadoop YARN Project",
            "status" : "SKIPPED",
            "timeElapsed" : 0.0
          }, {
            "moduleName" : "Apache Hadoop MapReduce HistoryServer Plugins",
            "status" : "SKIPPED",
            "timeElapsed" : 0.0
          }, {
            "moduleName" : "Apache Hadoop MapReduce NativeTask",
            "status" : "SKIPPED",
            "timeElapsed" : 0.0
          }, {
            "moduleName" : "Apache Hadoop MapReduce Uploader",
            "status" : "SKIPPED",
            "timeElapsed" : 0.0
          }, {
            "moduleName" : "Apache Hadoop MapReduce Examples",
            "status" : "SKIPPED",
            "timeElapsed" : 0.0
          }, {
            "moduleName" : "Apache Hadoop MapReduce",
            "status" : "SKIPPED",
            "timeElapsed" : 0.0
          }, {
            "moduleName" : "Apache Hadoop MapReduce Streaming",
            "status" : "SKIPPED",
            "timeElapsed" : 0.0
          }, {
            "moduleName" : "Apache Hadoop Distributed Copy",
            "status" : "SKIPPED",
            "timeElapsed" : 0.0
          }, {
            "moduleName" : "Apache Hadoop Archives",
            "status" : "SKIPPED",
            "timeElapsed" : 0.0
          }, {
            "moduleName" : "Apache Hadoop Archive Logs",
            "status" : "SKIPPED",
            "timeElapsed" : 0.0
          }, {
            "moduleName" : "Apache Hadoop Rumen",
            "status" : "SKIPPED",
            "timeElapsed" : 0.0
          }, {
            "moduleName" : "Apache Hadoop Gridmix",
            "status" : "SKIPPED",
            "timeElapsed" : 0.0
          }, {
            "moduleName" : "Apache Hadoop Data Join",
            "status" : "SKIPPED",
            "timeElapsed" : 0.0
          }, {
            "moduleName" : "Apache Hadoop Extras",
            "status" : "SKIPPED",
            "timeElapsed" : 0.0
          }, {
            "moduleName" : "Apache Hadoop Pipes",
            "status" : "SUCCESS",
            "timeElapsed" : 0.051
          }, {
            "moduleName" : "Apache Hadoop OpenStack support",
            "status" : "SKIPPED",
            "timeElapsed" : 0.0
          }, {
            "moduleName" : "Apache Hadoop Amazon Web Services support",
            "status" : "SKIPPED",
            "timeElapsed" : 0.0
          }, {
            "moduleName" : "Apache Hadoop Kafka Library support",
            "status" : "SKIPPED",
            "timeElapsed" : 0.0
          }, {
            "moduleName" : "Apache Hadoop Azure support",
            "status" : "SKIPPED",
            "timeElapsed" : 0.0
          }, {
            "moduleName" : "Apache Hadoop Aliyun OSS support",
            "status" : "SKIPPED",
            "timeElapsed" : 0.0
          }, {
            "moduleName" : "Apache Hadoop Client Aggregator",
            "status" : "SKIPPED",
            "timeElapsed" : 0.0
          }, {
            "moduleName" : "Apache Hadoop Scheduler Load Simulator",
            "status" : "SKIPPED",
            "timeElapsed" : 0.0
          }, {
            "moduleName" : "Apache Hadoop Resource Estimator Service",
            "status" : "SKIPPED",
            "timeElapsed" : 0.0
          }, {
            "moduleName" : "Apache Hadoop Azure Data Lake support",
            "status" : "SKIPPED",
            "timeElapsed" : 0.0
          }, {
            "moduleName" : "Apache Hadoop Image Generation Tool",
            "status" : "SKIPPED",
            "timeElapsed" : 0.0
          }, {
            "moduleName" : "Apache Hadoop Tools Dist",
            "status" : "SKIPPED",
            "timeElapsed" : 0.0
          }, {
            "moduleName" : "Apache Hadoop Tools",
            "status" : "SUCCESS",
            "timeElapsed" : 0.04
          }, {
            "moduleName" : "Apache Hadoop Client API",
            "status" : "SKIPPED",
            "timeElapsed" : 0.0
          }, {
            "moduleName" : "Apache Hadoop Client Runtime",
            "status" : "SKIPPED",
            "timeElapsed" : 0.0
          }, {
            "moduleName" : "Apache Hadoop Client Packaging Invariants",
            "status" : "SKIPPED",
            "timeElapsed" : 0.0
          }, {
            "moduleName" : "Apache Hadoop Client Test Minicluster",
            "status" : "SKIPPED",
            "timeElapsed" : 0.0
          }, {
            "moduleName" : "Apache Hadoop Client Packaging Invariants for Test",
            "status" : "SKIPPED",
            "timeElapsed" : 0.0
          }, {
            "moduleName" : "Apache Hadoop Client Packaging Integration Tests",
            "status" : "SKIPPED",
            "timeElapsed" : 0.0
          }, {
            "moduleName" : "Apache Hadoop Distribution",
            "status" : "SKIPPED",
            "timeElapsed" : 0.0
          }, {
            "moduleName" : "Apache Hadoop Client Modules",
            "status" : "SUCCESS",
            "timeElapsed" : 0.063
          }, {
            "moduleName" : "Apache Hadoop Cloud Storage",
            "status" : "SKIPPED",
            "timeElapsed" : 0.0
          }, {
            "moduleName" : "Apache Hadoop Cloud Storage Project",
            "status" : "SUCCESS",
            "timeElapsed" : 0.038
          } ],
          "buildStatus" : "FAILURE",
          "totalTime" : 459.0
        },
        "testResults" : {
          "runNum" : 102,
          "failuresNum" : 0,
          "errorsNum" : 0,
          "skippedNum" : 0,
          "elapsedTime" : 97.204994,
          "projectDir" : "C:\\Users\\vova\\Documents\\BernUni\\Semester3\\Thesis\\ci-cd-merge-resolver\\ci-cd-merge-resolver\\temp\\projects\\hadoop_0"
        },
        "conflictPatterns" : {
          "hadoop-hdds\\container-service\\src\\main\\java\\org\\apache\\hadoop\\ozone\\container\\ozoneimpl\\ContainerReader.java" : [ "OursPattern" ]
        }
      }, {
        "variantName" : "hadoop_1",
        "compilationResult" : {
          "moduleResults" : [ {
            "moduleName" : "Apache Hadoop Main",
            "status" : "SUCCESS",
            "timeElapsed" : 0.48
          }, {
            "moduleName" : "Apache Hadoop Build Tools",
            "status" : "SUCCESS",
            "timeElapsed" : 1.165
          }, {
            "moduleName" : "Apache Hadoop Project POM",
            "status" : "FAILURE",
            "timeElapsed" : 0.14
          }, {
            "moduleName" : "Apache Hadoop Annotations",
            "status" : "SKIPPED",
            "timeElapsed" : 0.0
          }, {
            "moduleName" : "Apache Hadoop Project Dist POM",
            "status" : "SKIPPED",
            "timeElapsed" : 0.0
          }, {
            "moduleName" : "Apache Hadoop Assemblies",
            "status" : "SKIPPED",
            "timeElapsed" : 0.0
          }, {
            "moduleName" : "Apache Hadoop Maven Plugins",
            "status" : "SKIPPED",
            "timeElapsed" : 0.0
          }, {
            "moduleName" : "Apache Hadoop MiniKDC",
            "status" : "SKIPPED",
            "timeElapsed" : 0.0
          }, {
            "moduleName" : "Apache Hadoop Auth",
            "status" : "SKIPPED",
            "timeElapsed" : 0.0
          }, {
            "moduleName" : "Apache Hadoop Auth Examples",
            "status" : "SKIPPED",
            "timeElapsed" : 0.0
          }, {
            "moduleName" : "Apache Hadoop Common",
            "status" : "SKIPPED",
            "timeElapsed" : 0.0
          }, {
            "moduleName" : "Apache Hadoop NFS",
            "status" : "SKIPPED",
            "timeElapsed" : 0.0
          }, {
            "moduleName" : "Apache Hadoop KMS",
            "status" : "SKIPPED",
            "timeElapsed" : 0.0
          }, {
            "moduleName" : "Apache Hadoop Registry",
            "status" : "SKIPPED",
            "timeElapsed" : 0.0
          }, {
            "moduleName" : "Apache Hadoop Common Project",
            "status" : "SKIPPED",
            "timeElapsed" : 0.0
          }, {
            "moduleName" : "Apache Hadoop HDFS Client",
            "status" : "SKIPPED",
            "timeElapsed" : 0.0
          }, {
            "moduleName" : "Apache Hadoop HDFS",
            "status" : "SKIPPED",
            "timeElapsed" : 0.0
          }, {
            "moduleName" : "Apache Hadoop HDFS Native Client",
            "status" : "SKIPPED",
            "timeElapsed" : 0.0
          }, {
            "moduleName" : "Apache Hadoop HttpFS",
            "status" : "SKIPPED",
            "timeElapsed" : 0.0
          }, {
            "moduleName" : "Apache Hadoop HDFS-NFS",
            "status" : "SKIPPED",
            "timeElapsed" : 0.0
          }, {
            "moduleName" : "Apache Hadoop HDFS-RBF",
            "status" : "SKIPPED",
            "timeElapsed" : 0.0
          }, {
            "moduleName" : "Apache Hadoop HDFS Project",
            "status" : "SKIPPED",
            "timeElapsed" : 0.0
          }, {
            "moduleName" : "Apache Hadoop YARN",
            "status" : "SKIPPED",
            "timeElapsed" : 0.0
          }, {
            "moduleName" : "Apache Hadoop YARN API",
            "status" : "SKIPPED",
            "timeElapsed" : 0.0
          }, {
            "moduleName" : "Apache Hadoop YARN Common",
            "status" : "SKIPPED",
            "timeElapsed" : 0.0
          }, {
            "moduleName" : "Apache Hadoop YARN Server",
            "status" : "SKIPPED",
            "timeElapsed" : 0.0
          }, {
            "moduleName" : "Apache Hadoop YARN Server Common",
            "status" : "SKIPPED",
            "timeElapsed" : 0.0
          }, {
            "moduleName" : "Apache Hadoop YARN NodeManager",
            "status" : "SKIPPED",
            "timeElapsed" : 0.0
          }, {
            "moduleName" : "Apache Hadoop YARN Web Proxy",
            "status" : "SKIPPED",
            "timeElapsed" : 0.0
          }, {
            "moduleName" : "Apache Hadoop YARN ApplicationHistoryService",
            "status" : "SKIPPED",
            "timeElapsed" : 0.0
          }, {
            "moduleName" : "Apache Hadoop YARN Timeline Service",
            "status" : "SKIPPED",
            "timeElapsed" : 0.0
          }, {
            "moduleName" : "Apache Hadoop YARN ResourceManager",
            "status" : "SKIPPED",
            "timeElapsed" : 0.0
          }, {
            "moduleName" : "Apache Hadoop YARN Server Tests",
            "status" : "SKIPPED",
            "timeElapsed" : 0.0
          }, {
            "moduleName" : "Apache Hadoop YARN Client",
            "status" : "SKIPPED",
            "timeElapsed" : 0.0
          }, {
            "moduleName" : "Apache Hadoop YARN SharedCacheManager",
            "status" : "SKIPPED",
            "timeElapsed" : 0.0
          }, {
            "moduleName" : "Apache Hadoop YARN Timeline Plugin Storage",
            "status" : "SKIPPED",
            "timeElapsed" : 0.0
          }, {
            "moduleName" : "Apache Hadoop YARN TimelineService HBase Backend",
            "status" : "SKIPPED",
            "timeElapsed" : 0.0
          }, {
            "moduleName" : "Apache Hadoop YARN TimelineService HBase Common",
            "status" : "SKIPPED",
            "timeElapsed" : 0.0
          }, {
            "moduleName" : "Apache Hadoop YARN TimelineService HBase Client",
            "status" : "SKIPPED",
            "timeElapsed" : 0.0
          }, {
            "moduleName" : "Apache Hadoop YARN TimelineService HBase Servers",
            "status" : "SKIPPED",
            "timeElapsed" : 0.0
          }, {
            "moduleName" : "Apache Hadoop YARN TimelineService HBase Server 1.2",
            "status" : "SKIPPED",
            "timeElapsed" : 0.0
          }, {
            "moduleName" : "Apache Hadoop YARN TimelineService HBase tests",
            "status" : "SKIPPED",
            "timeElapsed" : 0.0
          }, {
            "moduleName" : "Apache Hadoop YARN Router",
            "status" : "SKIPPED",
            "timeElapsed" : 0.0
          }, {
            "moduleName" : "Apache Hadoop YARN TimelineService DocumentStore",
            "status" : "SKIPPED",
            "timeElapsed" : 0.0
          }, {
            "moduleName" : "Apache Hadoop YARN Applications",
            "status" : "SKIPPED",
            "timeElapsed" : 0.0
          }, {
            "moduleName" : "Apache Hadoop YARN DistributedShell",
            "status" : "SKIPPED",
            "timeElapsed" : 0.0
          }, {
            "moduleName" : "Apache Hadoop YARN Unmanaged Am Launcher",
            "status" : "SKIPPED",
            "timeElapsed" : 0.0
          }, {
            "moduleName" : "Apache Hadoop MapReduce Client",
            "status" : "SKIPPED",
            "timeElapsed" : 0.0
          }, {
            "moduleName" : "Apache Hadoop MapReduce Core",
            "status" : "SKIPPED",
            "timeElapsed" : 0.0
          }, {
            "moduleName" : "Apache Hadoop MapReduce Common",
            "status" : "SKIPPED",
            "timeElapsed" : 0.0
          }, {
            "moduleName" : "Apache Hadoop MapReduce Shuffle",
            "status" : "SKIPPED",
            "timeElapsed" : 0.0
          }, {
            "moduleName" : "Apache Hadoop MapReduce App",
            "status" : "SKIPPED",
            "timeElapsed" : 0.0
          }, {
            "moduleName" : "Apache Hadoop MapReduce HistoryServer",
            "status" : "SKIPPED",
            "timeElapsed" : 0.0
          }, {
            "moduleName" : "Apache Hadoop MapReduce JobClient",
            "status" : "SKIPPED",
            "timeElapsed" : 0.0
          }, {
            "moduleName" : "Apache Hadoop Mini-Cluster",
            "status" : "SKIPPED",
            "timeElapsed" : 0.0
          }, {
            "moduleName" : "Apache Hadoop YARN Services",
            "status" : "SKIPPED",
            "timeElapsed" : 0.0
          }, {
            "moduleName" : "Apache Hadoop YARN Services Core",
            "status" : "SKIPPED",
            "timeElapsed" : 0.0
          }, {
            "moduleName" : "Apache Hadoop YARN Services API",
            "status" : "SKIPPED",
            "timeElapsed" : 0.0
          }, {
            "moduleName" : "Apache Hadoop YARN Application Catalog",
            "status" : "SKIPPED",
            "timeElapsed" : 0.0
          }, {
            "moduleName" : "Apache Hadoop YARN Application Catalog Webapp",
            "status" : "SKIPPED",
            "timeElapsed" : 0.0
          }, {
            "moduleName" : "Apache Hadoop YARN Application Catalog Docker Image",
            "status" : "SKIPPED",
            "timeElapsed" : 0.0
          }, {
            "moduleName" : "Apache Hadoop YARN Application MaWo",
            "status" : "SKIPPED",
            "timeElapsed" : 0.0
          }, {
            "moduleName" : "Apache Hadoop YARN Application MaWo Core",
            "status" : "SKIPPED",
            "timeElapsed" : 0.0
          }, {
            "moduleName" : "Apache Hadoop YARN Site",
            "status" : "SKIPPED",
            "timeElapsed" : 0.0
          }, {
            "moduleName" : "Apache Hadoop YARN Registry",
            "status" : "SKIPPED",
            "timeElapsed" : 0.0
          }, {
            "moduleName" : "Apache Hadoop YARN UI",
            "status" : "SKIPPED",
            "timeElapsed" : 0.0
          }, {
            "moduleName" : "Apache Hadoop YARN CSI",
            "status" : "SKIPPED",
            "timeElapsed" : 0.0
          }, {
            "moduleName" : "Apache Hadoop YARN Project",
            "status" : "SKIPPED",
            "timeElapsed" : 0.0
          }, {
            "moduleName" : "Apache Hadoop MapReduce HistoryServer Plugins",
            "status" : "SKIPPED",
            "timeElapsed" : 0.0
          }, {
            "moduleName" : "Apache Hadoop MapReduce NativeTask",
            "status" : "SKIPPED",
            "timeElapsed" : 0.0
          }, {
            "moduleName" : "Apache Hadoop MapReduce Uploader",
            "status" : "SKIPPED",
            "timeElapsed" : 0.0
          }, {
            "moduleName" : "Apache Hadoop MapReduce Examples",
            "status" : "SKIPPED",
            "timeElapsed" : 0.0
          }, {
            "moduleName" : "Apache Hadoop MapReduce",
            "status" : "SKIPPED",
            "timeElapsed" : 0.0
          }, {
            "moduleName" : "Apache Hadoop MapReduce Streaming",
            "status" : "SKIPPED",
            "timeElapsed" : 0.0
          }, {
            "moduleName" : "Apache Hadoop Distributed Copy",
            "status" : "SKIPPED",
            "timeElapsed" : 0.0
          }, {
            "moduleName" : "Apache Hadoop Archives",
            "status" : "SKIPPED",
            "timeElapsed" : 0.0
          }, {
            "moduleName" : "Apache Hadoop Archive Logs",
            "status" : "SKIPPED",
            "timeElapsed" : 0.0
          }, {
            "moduleName" : "Apache Hadoop Rumen",
            "status" : "SKIPPED",
            "timeElapsed" : 0.0
          }, {
            "moduleName" : "Apache Hadoop Gridmix",
            "status" : "SKIPPED",
            "timeElapsed" : 0.0
          }, {
            "moduleName" : "Apache Hadoop Data Join",
            "status" : "SKIPPED",
            "timeElapsed" : 0.0
          }, {
            "moduleName" : "Apache Hadoop Extras",
            "status" : "SKIPPED",
            "timeElapsed" : 0.0
          }, {
            "moduleName" : "Apache Hadoop Pipes",
            "status" : "SKIPPED",
            "timeElapsed" : 0.0
          }, {
            "moduleName" : "Apache Hadoop OpenStack support",
            "status" : "SKIPPED",
            "timeElapsed" : 0.0
          }, {
            "moduleName" : "Apache Hadoop Amazon Web Services support",
            "status" : "SKIPPED",
            "timeElapsed" : 0.0
          }, {
            "moduleName" : "Apache Hadoop Kafka Library support",
            "status" : "SKIPPED",
            "timeElapsed" : 0.0
          }, {
            "moduleName" : "Apache Hadoop Azure support",
            "status" : "SKIPPED",
            "timeElapsed" : 0.0
          }, {
            "moduleName" : "Apache Hadoop Aliyun OSS support",
            "status" : "SKIPPED",
            "timeElapsed" : 0.0
          }, {
            "moduleName" : "Apache Hadoop Client Aggregator",
            "status" : "SKIPPED",
            "timeElapsed" : 0.0
          }, {
            "moduleName" : "Apache Hadoop Scheduler Load Simulator",
            "status" : "SKIPPED",
            "timeElapsed" : 0.0
          }, {
            "moduleName" : "Apache Hadoop Resource Estimator Service",
            "status" : "SKIPPED",
            "timeElapsed" : 0.0
          }, {
            "moduleName" : "Apache Hadoop Azure Data Lake support",
            "status" : "SKIPPED",
            "timeElapsed" : 0.0
          }, {
            "moduleName" : "Apache Hadoop Image Generation Tool",
            "status" : "SKIPPED",
            "timeElapsed" : 0.0
          }, {
            "moduleName" : "Apache Hadoop Tools Dist",
            "status" : "SKIPPED",
            "timeElapsed" : 0.0
          }, {
            "moduleName" : "Apache Hadoop Tools",
            "status" : "SKIPPED",
            "timeElapsed" : 0.0
          }, {
            "moduleName" : "Apache Hadoop Client API",
            "status" : "SKIPPED",
            "timeElapsed" : 0.0
          }, {
            "moduleName" : "Apache Hadoop Client Runtime",
            "status" : "SKIPPED",
            "timeElapsed" : 0.0
          }, {
            "moduleName" : "Apache Hadoop Client Packaging Invariants",
            "status" : "SKIPPED",
            "timeElapsed" : 0.0
          }, {
            "moduleName" : "Apache Hadoop Client Test Minicluster",
            "status" : "SKIPPED",
            "timeElapsed" : 0.0
          }, {
            "moduleName" : "Apache Hadoop Client Packaging Invariants for Test",
            "status" : "SKIPPED",
            "timeElapsed" : 0.0
          }, {
            "moduleName" : "Apache Hadoop Client Packaging Integration Tests",
            "status" : "SKIPPED",
            "timeElapsed" : 0.0
          }, {
            "moduleName" : "Apache Hadoop Distribution",
            "status" : "SKIPPED",
            "timeElapsed" : 0.0
          }, {
            "moduleName" : "Apache Hadoop Client Modules",
            "status" : "SKIPPED",
            "timeElapsed" : 0.0
          }, {
            "moduleName" : "Apache Hadoop Cloud Storage",
            "status" : "SKIPPED",
            "timeElapsed" : 0.0
          }, {
            "moduleName" : "Apache Hadoop Cloud Storage Project",
            "status" : "SKIPPED",
            "timeElapsed" : 0.0
          } ],
          "buildStatus" : "FAILURE",
          "totalTime" : 4.172
        },
        "testResults" : {
          "runNum" : 102,
          "failuresNum" : 0,
          "errorsNum" : 0,
          "skippedNum" : 0,
          "elapsedTime" : 97.204994,
          "projectDir" : "C:\\Users\\vova\\Documents\\BernUni\\Semester3\\Thesis\\ci-cd-merge-resolver\\ci-cd-merge-resolver\\temp\\projects\\hadoop_1"
        },
        "conflictPatterns" : {
          "hadoop-hdds\\container-service\\src\\main\\java\\org\\apache\\hadoop\\ozone\\container\\ozoneimpl\\ContainerReader.java" : [ "TheirsPattern" ]
        }
      } ]
    }
  } ]
}